{
  "mappings": [
    {"aliases": ["hEDS", "SEDh", "SED hipermóvil", "SED hiperlaxo", "Ehlers-Danlos hiperlaxo"], "icd10": "Q79.60", "label": "Síndrome de Ehlers-Danlos, hiperlaxo"},
    {"aliases": ["clEDS", "EDS clásico", "Ehlers-Danlos clásico"], "icd10": "Q79.61", "label": "Síndrome de Ehlers-Danlos, clásico"},
    {"aliases": ["vEDS", "EDS vascular", "Ehlers-Danlos vascular"], "icd10": "Q79.62", "label": "Síndrome de Ehlers-Danlos, vascular"},
    {"aliases": ["EDS", "SED", "Ehlers-Danlos"], "icd10": "Q79.6", "label": "Síndrome de Ehlers-Danlos"},
    {"aliases": ["HSD", "Hipermovilidad", "Síndrome de hipermovilidad"], "icd10": "M35.7", "label": "Síndrome de hipermovilidad"},
    {"aliases": ["POTS", "Taquicardia ortostática", "Síndrome de taquicardia ortostática postural"], "icd10": "G90.A", "label": "Síndrome de taquicardia ortostática postural"},
    {"aliases": ["Dysautonomia", "Disautonomía"], "icd10": "G90.9", "label": "Disautonomía"},
    {"aliases": ["MCAS", "Síndrome de activación mastocitaria"], "icd10": "D89.40", "label": "Síndrome de activación de mastocitos"},
    {"aliases": ["Fibromyalgia", "Fibromialgia"], "icd10": "M79.7", "label": "Fibromialgia"},
    {"aliases": ["Gastroparesis", "Gastroparesia"], "icd10": "K31.84", "label": "Gastroparesia"},
    {"aliases": ["Adenomyosis", "Adenomiosis"], "icd10": "N80.0", "label": "Adenomiosis"},
    {"aliases": ["Endometriosis"], "icd10": "N80.9", "label": "Endometriosis"},
    {"aliases": ["Anemia"], "icd10": "D64.9", "label": "Anemia"},
    {"aliases": ["Migraine", "Migraña"], "icd10": "G43.9", "label": "Migraña"},
    {"aliases": ["IBS", "Síndrome de intestino irritable"], "icd10": "K58.9", "label": "Síndrome de colon irritable"},
    {"aliases": ["Anxiety", "Ansiedad"], "icd10": "F41.9", "label": "Trastorno de ansiedad"},
    {"aliases": ["Depression", "Depresión"], "icd10": "F32.9", "label": "Trastorno depresivo"},
    {"aliases": ["ADHD", "TDAH"], "icd10": "F90.9", "label": "Trastorno por déficit de atención e hiperactividad"},
    {"aliases": ["Autism", "Autismo", "TEA"], "icd10": "F84.0", "label": "Trastorno del espectro autista"},
    {"aliases": ["CCI", "Inestabilidad craneocervical", "Inestabilidad atlantoaxial", "ICC"], "icd10": "M53.2", "label": "Inestabilidad espinal (Craneocervical)"},
    {"aliases": ["Chiari", "Malformación de Chiari", "Arnold-Chiari", "CMI"], "icd10": "Q07.0", "label": "Síndrome de Arnold-Chiari"},
    {"aliases": ["Tethered cord", "Médula anclada", "Síndrome de médula anclada", "SMA"], "icd10": "Q06.8", "label": "Otras malformaciones congénitas de la médula espinal (Médula anclada)"},
    {"aliases": ["ME/CFS", "SFC", "Síndrome de fatiga crónica", "Encefalomielitis miálgica"], "icd10": "G93.3", "label": "Síndrome de fatiga posviral / Encefalomielitis miálgica"},
    {"aliases": ["MPS", "Dolor miofascial", "Síndrome de dolor miofascial", "Puntos gatillo"], "icd10": "M79.1", "label": "Mialgia / Síndrome de dolor miofascial"},
    {"aliases": ["TMJ", "TMD", "ATM", "Trastorno temporomandibular", "Dolor mandibular"], "icd10": "K07.6", "label": "Trastornos de la articulación temporomandibular"},
    {"aliases": ["Luxaciones recurrentes", "Subluxaciones", "Inestabilidad articular", "Dislocación"], "icd10": "M24.4", "label": "Luxación y subluxación recidivante de la articulación"},
    {"aliases": ["Osteoartritis prematura", "Artrosis", "Osteoartrosis"], "icd10": "M19.9", "label": "Artrosis, no especificada"},
    {"aliases": ["Costocondritis", "Dolor de costillas", "Síndrome de Tietze"], "icd10": "M94.0", "label": "Síndrome de la articulación condrocostal (Tietze)"},
    {"aliases": ["GERD", "ERGE", "Reflujo", "Reflujo gastroesofágico"], "icd10": "K21.9", "label": "Enfermedad por reflujo gastroesofágico sin esofagitis"},
    {"aliases": ["SIBO", "Sobrecrecimiento bacteriano", "Sobrecrecimiento bacteriano en el intestino delgado"], "icd10": "K90.89", "label": "Otros trastornos de malabsorción intestinal especificados (SIBO)"},
    {"aliases": ["Hernia de hiato", "Hernia hiatal"], "icd10": "K44.9", "label": "Hernia diafragmática sin obstrucción ni gangrena"},
    {"aliases": ["OH", "Hipotensión ortostática", "Baja presión al ponerse de pie"], "icd10": "I95.1", "label": "Hipotensión ortostática"},
    {"aliases": ["MVP", "Prolapso mitral", "Prolapso de la válvula mitral"], "icd10": "I34.1", "label": "Prolapso de la válvula mitral (no reumático)"},
    {"aliases": ["Raynaud", "Síndrome de Raynaud", "Fenómeno de Raynaud"], "icd10": "I73.0", "label": "Síndrome de Raynaud"},
    {"aliases": ["RLS", "SPI", "Piernas inquietas", "Síndrome de piernas inquietas"], "icd10": "G25.81", "label": "Síndrome de las piernas inquietas"},
    {"aliases": ["Sleep Apnea", "Apnea del sueño", "SAOS"], "icd10": "G47.33", "label": "Apnea obstructiva del sueño"},
    {"aliases": ["PCOS", "SOP", "Síndrome de ovario poliquístico"], "icd10": "E28.2", "label": "Síndrome de ovario poliquístico"},
    {"aliases": ["Pelvic Organ Prolapse", "POP", "Prolapso pélvico", "Prolapso de órganos pélvicos"], "icd10": "N81.9", "label": "Prolapso genital femenino, no especificado"}
  ]
}